EYPA/EYPA.py
EYPA/__init__.py
EYPA/test.py
EYPA-0.0.0.0.0.0.2.6.dist-info/METADATA
EYPA-0.0.0.0.0.0.2.6.dist-info/WHEEL
EYPA-0.0.0.0.0.0.2.6.dist-info/top_level.txt
EYPA-0.0.0.0.0.0.2.6.dist-info/RECORD
