Metadata-Version: 2.1
Name: EYPA
Version: 0.0.0.0.0.0.2.6
Summary: UNKNOWN
Home-page: UNKNOWN
License: UNKNOWN
Platform: UNKNOWN
